unlimit_package_build_tutorial/main.py
unlimit_package_build_tutorial/templates/store.html
unlimit_package_build_tutorial-0.1.0.dist-info/METADATA
unlimit_package_build_tutorial-0.1.0.dist-info/WHEEL
unlimit_package_build_tutorial-0.1.0.dist-info/entry_points.txt
unlimit_package_build_tutorial-0.1.0.dist-info/RECORD
